AUTHORS
LICENSE
MANIFEST.in
README.rst
setup.cfg
setup.py
multimerchant/__init__.py
multimerchant/_version.py
multimerchant/network.py
multimerchant.egg-info/PKG-INFO
multimerchant.egg-info/SOURCES.txt
multimerchant.egg-info/dependency_links.txt
multimerchant.egg-info/requires.txt
multimerchant.egg-info/top_level.txt
multimerchant/wallet/__init__.py
multimerchant/wallet/bip32.py
multimerchant/wallet/keys.py
multimerchant/wallet/utils.py