Metadata-Version: 1.1
Name: multimerchant
Version: 0.0.1
Summary: Bitcoin/Dogecoin/Litecoin merchant tools that work with Block.io
Home-page: https://github.com/blockio/multimerchant-python
Author: Steven Buss
Author-email: steven.buss@gmail.com
License: MIT License
Download-URL: https://github.com/blockio/multimerchant-python/tarball/v0.0.1
Platform: UNKNOWN
Classifier: Development Status :: 3 - Alpha
Classifier: Intended Audience :: Developers
Classifier: License :: OSI Approved :: MIT License
Classifier: Operating System :: OS Independent
Classifier: Programming Language :: Python
Classifier: Programming Language :: Python :: 2.6
Classifier: Programming Language :: Python :: 2.7
Classifier: Programming Language :: Python :: 3
Classifier: Programming Language :: Python :: 3.3
